downpyment/__init__.py
downpyment/amortization.py
downpyment/interest.py
downpyment/investment.py
downpyment/reporting.py
downpyment/utils.py
downpyment/mortgage/__init__.py
downpyment/mortgage/mortgage.py
downpyment/mortgage/simulation.py
downpyment-0.1.1.dist-info/METADATA
downpyment-0.1.1.dist-info/WHEEL
downpyment-0.1.1.dist-info/RECORD
