Metadata-Version: 2.4
Name: downpyment
Version: 0.1.1
Summary: Utilities for mortgage analysis and visualization
Requires-Python: >=3.10
Requires-Dist: matplotlib>=3.10.7
